exonum_launcher_cis/__init__.py
exonum_launcher_cis/__main__.py
exonum_launcher_cis/action_result.py
exonum_launcher_cis/cli.py
exonum_launcher_cis/configuration.py
exonum_launcher_cis/explorer.py
exonum_launcher_cis/launch_state.py
exonum_launcher_cis/launcher.py
exonum_launcher_cis/main.py
exonum_launcher_cis/supervisor.py
exonum_launcher_cis/instances/__init__.py
exonum_launcher_cis/instances/default_spec_loader.py
exonum_launcher_cis/instances/instance_spec_loader.py
exonum_launcher_cis/runtimes/__init__.py
exonum_launcher_cis/runtimes/python.py
exonum_launcher_cis/runtimes/runtime.py
exonum_launcher_cis/runtimes/rust.py
exonum_launcher_cis-0.1.3.dist-info/LICENSE
exonum_launcher_cis-0.1.3.dist-info/METADATA
exonum_launcher_cis-0.1.3.dist-info/WHEEL
exonum_launcher_cis-0.1.3.dist-info/top_level.txt
exonum_launcher_cis-0.1.3.dist-info/RECORD
