Metadata-Version: 2.1
Name: exonum-launcher-cis
Version: 0.1.3
Summary: Exonum CIS Dynamic Services Launcher
Home-page: UNKNOWN
Author: The Exonum team
Author-email: contact@exonum.com
License: UNKNOWN
Platform: UNKNOWN
Classifier: Programming Language :: Python :: 3
Classifier: License :: OSI Approved :: Apache Software License
Classifier: Operating System :: OS Independent
Classifier: Topic :: Security :: Cryptography
Requires-Python: >=3.6
Requires-Dist: pyyaml
Requires-Dist: exonum-python-client (==0.4.0.dev4)
